amoniak/__init__.py
amoniak/amon.py
amoniak/cache.py
amoniak/runner.py
amoniak/tasks.py
amoniak/utils.py
amoniak/caching/__init__.py
amoniak/caching/ot101results.py
amoniak/caching/ot103results.py
amoniak/caching/ot201results.py
amoniak/caching/ot401results.py
amoniak/caching/ot503results.py
amoniak/caching/results.py
amoniak-1.0.2.dist-info/LICENSE
amoniak-1.0.2.dist-info/METADATA
amoniak-1.0.2.dist-info/WHEEL
amoniak-1.0.2.dist-info/entry_points.txt
amoniak-1.0.2.dist-info/top_level.txt
amoniak-1.0.2.dist-info/RECORD
